pymimir_rgnn/__init__.py
pymimir_rgnn/aggregations.py
pymimir_rgnn/bases.py
pymimir_rgnn/configs.py
pymimir_rgnn/decoders.py
pymimir_rgnn/encoders.py
pymimir_rgnn/messages.py
pymimir_rgnn/model.py
pymimir_rgnn/modules.py
pymimir_rgnn/updates.py
pymimir_rgnn/utils.py
pymimir_rgnn-0.2.3.dist-info/licenses/LICENSE
pymimir_rgnn-0.2.3.dist-info/METADATA
pymimir_rgnn-0.2.3.dist-info/WHEEL
pymimir_rgnn-0.2.3.dist-info/top_level.txt
pymimir_rgnn-0.2.3.dist-info/RECORD
